LICENSE
MANIFEST.in
README.md
setup.cfg
setup.py
tf2helm/filehandler.py
tf2helm/tf2helm.py
tf2helm/tfparser.py
tf2helm.egg-info/PKG-INFO
tf2helm.egg-info/SOURCES.txt
tf2helm.egg-info/dependency_links.txt
tf2helm.egg-info/entry_points.txt
tf2helm.egg-info/requires.txt
tf2helm.egg-info/top_level.txt
tf2helm/files/_helpers.tpl
tf2helm/templates/isaaguilar.yaml.j2
tf2helm/templates/oam-terraform-controller.yaml.j2
tf2helm/templates/terraform-controller.yaml.j2