Metadata-Version: 2.1
Name: tf2helm
Version: 0.0.23
Summary: tf2helm converts a Terraform module to a Helm Chart
Home-page: https://github.com/appvia/tf2helm
Author: Mohammud Yassine Jaffoo
Author-email: yassine.jaffoo@jaffoosolutions.com
License: UNKNOWN
Keywords: terraform,helm,kubernetes,self-service,cloud,aws,azure,gcp
Platform: UNKNOWN
Classifier: Development Status :: 3 - Alpha
Classifier: Intended Audience :: Developers
Classifier: License :: OSI Approved :: Apache Software License
Classifier: Operating System :: OS Independent
Classifier: Programming Language :: Python
Classifier: Programming Language :: Python :: 3
Classifier: Programming Language :: Python :: 3.3
Classifier: Programming Language :: Python :: 3.4
Classifier: Topic :: Text Processing
